[
{"tokens": ["If", "you", "'ve", "ever", "experienced", "terrible", "service", ",", "you", "know", "the", "irritable", "feeling", "that", "builds", "and", "builds", "as", "you", "sit", "for", "20", "minutes", "and", "watch", "the", "tables", "around", "you", "being", "seated", "and", "waited", "on", "until", "you", "'re", "finally", "''", "``", "greeted", "''", "''", "by", "a", "surly", "waitress", "rushing", "you", "to", "order", "after", "she", "finally", "decides", "to", "waddle", "her", "way", "to", "your", "table", "."], "e1_text": "order", "e1_pos": 50, "e2_text": "decides", "e2_pos": 54, "label": "after"},
{"tokens": ["I", "had", "some", "high", "expectations", "for", "the", "place", "because", "I", "'d", "heard", "everyone", "rave", "on", "about", "it", ",", "so", "I", "was", "patient", "and", "enjoyed", "the", "cheese", "crisp", "appetizer", "that", "came", "15", "minutes", "after", "ordering", "it", "while", "the", "table", "of", "three", "directly", "across", "from", "my", "duet", "table", "enjoyed", "the", "meal", "they", "ordered", "after", "they", "sat", "down", "15", "minutes", "behind", "us", "."], "e1_text": "came", "e1_pos": 29, "e2_text": "ordering", "e2_pos": 33, "label": "after"},
{"tokens": ["I", "suppose", "she", "had", "already", "kissed", "her", "tip", "goodbye", "when", "she", "came", "to", "see", "if", "we", "needed", "anything", "a", "couple", "of", "minutes", "after", "we", "finally", "got", "our", "food", "-LRB-", "from", "someone", "else", "-RRB-", "and", "we", "asked", "for", "the", "check", "-LRB-", "since", "we", "did", "n't", "want", "to", "wait", "until", "closing", "to", "get", "it", "-RRB-", ",", "because", "she", "was", "sure", "to", "impart", "upon", "us", "a", "sassy", ",", "''", "``", "I", "will", "if", "you", "'ll", "give", "me", "a", "minute", "''", "''", "."], "e1_text": "needed", "e1_pos": 16, "e2_text": "got", "e2_pos": 25, "label": "after"}
]
