[
{"tokens": ["Plus", ",", "he", "was", "down", "to", "earth", "and", "real", ",", "nice", "change", "for", "a", "salon", ";--RRB-", "I", "have", "long", "thick", "hair", ",", "so", "is", "easy", "to", "tell", "if", "someone", "screws", "up", ",", "but", "he", "did", "a", "great", "job", ",", "and", "he", "even", "fixed", "my", "bangs", "-LRB-", "that", "I", "ineffectively", "tried", "to", "do", "the", "week", "before", ";--RRB-", "Will", "definitely", "go", "back", "."], "e1_text": "do", "e1_pos": 51, "e2_text": "go", "e2_pos": 58, "label": "before"}
]
