[
{"tokens": ["Pros", ":", "try", "before", "you", "buy", "A", "nice", "coach", "for", "your", "swing", "is", "available", "very", "well", "kept", "Misters", "for", "the", "heat", "Perfect", "real", "feeling", "mats", "Electronic", "adjustable", "tee", "'s", "Cons", ":", "Lots", "of", "noise", "and", "small", "kids", "running", "around", "expensive", "overpriced", "clubs", "if", "you", "want", "to", "buy", "after", "you", "try", "I", "cream", "the", "back", "net", "which", "is", "maybe", "230-240", "yards", "deep", "and", "not", "know", "how", "long", "my", "driver", "really", "is", "or", "its", "roll", "confusing", "single", "entrance", "Prices", ":", "6.00", "for", "50", "9.00", "for", "75", "11.00", "for", "100", "etc.", "."], "e1_text": "try", "e1_pos": 2, "e2_text": "buy", "e2_pos": 5, "label": "before"}
]
