[
{"tokens": ["Then", ",", "throughout", "the", "meal", ",", "he", "proceeded", "to", "commit", "two", "cardinal", "sins", "in", "a", "restaurant", ":", "asking", "if", "we", "were", "doing", "okay", "with", "his", "hands", "full", "and", "his", "back", "3\\/4", "turned", "away", "from", "us", ",", "as", "though", "we", "were", "an", "afterthought", ",", "and", "the", "second", ",", "putting", "the", "check", "down", "before", "asking", "if", "we", "wanted", "anything", "else", "."], "e1_text": "putting", "e1_pos": 47, "e2_text": "asking", "e2_pos": 17, "label": "before"}
]
