[
{"tokens": ["2nd", ",", "why", "my", "to", "go", "order", "for", "SOUP", "took", "39", "minutes", "to", "get", "to", "me", "from", "the", "time", "i", "called", "is", "beyond", "my", "explanation", ",", "i", "know", "you", "guys", "did", "n't", "make", "this", "fresh", "i", "know", "it", "was", "sitting", "in", "a", "big", "vat", "with", "maybe", "just", "the", "garnishing", "put", "on", "right", "before", "it", "went", "out", "so", "why", "the", "delay", "?"], "e1_text": "put", "e1_pos": 49, "e2_text": "went", "e2_pos": 54, "label": "before"}
]
