[
{"tokens": ["Although", "regretfully", ",", "I", "did", "n't", "partake", "in", "as", "much", "all-you-can-eat", "action", "as", "I", "would", "have", "liked", "-LRB-", "we", "ended", "up", "drinking", "8", "bottles", "of", "warm", "sake", "between", "3", "people", ",", "which", "can", "really", "kill", "an", "appetite", "-RRB-", ",", "what", "I", "did", "experience", "-LRB-", "before", "inebriation", "took", "over", "-RRB-", "was", "crisp", ",", "clean", "sushi", "and", "a", "wide", "variety", "of", "tasty", "rolls", "."], "e1_text": "did", "e1_pos": 4, "e2_text": "took", "e2_pos": 46, "label": "before"}
]
