[
{"tokens": ["generic", "sports", "bar\\/pub", "at", "the", "monte", "carlo", "...", "we", "were", "staying", "here", "and", "needed", "a", "place", "to", "rest", "before", "leaving", "for", "the", "airport", "...", "luckily", "it", "was", "happy", "hour", "so", "the", "cheap", "beers", "and", "$", "1", "wings", "and", "sliders", "was", "a", "good", "deal", "and", "a", "good", "way", "to", "cover", "some", "time", "...", "would", "n't", "suggest", "this", "as", "a", "must-stop", "though", "!"], "e1_text": "rest", "e1_pos": 17, "e2_text": "leaving", "e2_pos": 19, "label": "before"}
]
