[
{"tokens": ["we", "ordered", "the", "buffalo", "chicken", "medallions", "for", "appetizer", "...", "which", "were", "at", "best", "average", "...", "my", "top", "shelf", "long", "island", "was", "average", "...", "food", "delivery", "was", "slow", "and", "the", "bartender", "was", "occupied", "for", "a", "whoke", "before", "taking", "our", "order", "...", "the", "bathrooms", "are", "dated", "...", "it", "seems", "like", "this", "restaurant", "is", "catered", "to", "50", "+", "...", "the", "dining", "hall", "was", "not", "busy", "but", "our", "appetizer", "took", "nearly", "20", "minutes", "to", "come", "out", "and", "our", "entree", "over", "30", "minutes", ".", "."], "e1_text": "was", "e1_pos": 20, "e2_text": "taking", "e2_pos": 36, "label": "before"}
]
