[
{"tokens": ["To", "save", "lots", "of", "typing", "and", "explaining", ",", "after", "a", "few", "doctor", "visits", "it", "was", "concluded", "that", "the", "cause", "of", "the", "rash", "was", "from", "''", "``", "dirty", "needles", "''", "''", "as", "my", "doctor", "put", "it", "...", "After", "many", "more", "painful", "visits", "to", "the", "doctor", "the", "rash", "was", "finally", "removed", "and", "kicked", "from", "my", "system", "."], "e1_text": "save", "e1_pos": 1, "e2_text": "visits", "e2_pos": 12, "label": "after"}
]
