[
{"tokens": ["But", "let", "'s", "get", "to", "the", "BEST", "part", "...", "we", "could", "n't", "stop", "talking", "about", "how", "bad", "this", "meal", "was", "after", "we", "left", "-LRB-", "we", "literally", "had", "bets", "on", "which", "fast", "food", "restaurant", "they", "bought", "the", "burgers", "at", "-RRB-", ",", "so", "when", "we", "all", "got", "back", "to", "our", "house", ",", "my", "husband", "-LRB-", "an", "attorney", "-RRB-", "called", "the", "restaurant", "and", "got", "the", "manager", "on", "the", "phone", "to", "admit", "that", "half", "of", "their", "kitchen", "staff", "was", "absent", "and", "that", "they", "had", "bought", "the", "burgers", "elsewhere", "."], "e1_text": "was", "e1_pos": 19, "e2_text": "left", "e2_pos": 22, "label": "after"}
]
