[
{"tokens": ["It", "took", "forever", "T.T", "-LRB-", "about", "10", "minutes", "later", "-RRB-", "someone", "asked", "what", "we", "gon", "na", "order", "with", "a", "poker", "face", "...", "I", "told", "them", "I", "was", "ready", "to", "order", "everything", "to", "go", "but", "he", "said", "he", "can", "only", "take", "the", "drink", "order", ",", "so", "I", "ordered", "a", "Fiji", "bottled", "water", "and", "he", "just", "left", ",", "I", "had", "to", "wait", "15", "additional", "minutes", "just", "to", "flag", "down", "a", "waiter", "after", "being", "constantly", "ignored", "by", "whoever", "saw", "me", "-LRB-", "bus", "person", "?", "-RRB-"], "e1_text": "flag", "e1_pos": 65, "e2_text": "being", "e2_pos": 70, "label": "after"},
{"tokens": ["The", "whole", "process", "took", "more", "than", "50", "mins", ",", "the", "food", "was", "just", "mediocre", "but", "the", "price", "was", "on", "the", "upper", "side", ",", "now", "I", "would", "imagine", "a", "place", "with", "this", "price", "point", "in", "this", "fancy", "hotel", "would", "have", "a", "decent", "service", "Bottom", "line", ",", "If", "u", "just", "came", "back", "to", "the", "hotel", "after", "clubbing", "with", "a", "group", "of", "friends", "and", "did", "n't", "mind", "waiting", "for", "food", "while", "u", "sober", "up", "\\/", "or", "kept", "drinking", ",", "this", "place", "is", "okay", "But", "if", "u", "want", "a", "quick", "meal", ",", "I", "would", "suggest", "room", "service", "instead", "!"], "e1_text": "came", "e1_pos": 48, "e2_text": "clubbing", "e2_pos": 54, "label": "after"}
]
