[
{"tokens": ["This", "was", "followed", "by", "a", "crock", "of", "tasty", "and", "cheesy", "French", "Onion", "Soup", ",", "before", "enjoying", "a", "''", "``", "Chicago", "Style", "''", "''", "Garbage", "Salad", "which", "was", "small", "but", "very", "yummy", ",", "boasting", "chopped", "Iceberg", "Lettuce", ",", "tomato", ",", "Artichoke", "Hearts", ",", "Kalamata", "Olives", ",", "marinated", "mushrooms", ",", "Genoa", "Salami", ",", "cucumber", ",", "unmarinated", "mushrooms", ",", "sweet", "onions", ",", "Garbanzo", "Beans", ",", "and", "Cheddar", "Cheese", "with", "a", "light", "Lemon", "Vinaigrette", "Dressing", "."], "e1_text": "followed", "e1_pos": 2, "e2_text": "enjoying", "e2_pos": 15, "label": "before"}
]
