[
{"tokens": ["We", "did", "n't", "get", "our", "drinks", "refilled", "and", "barely", "got", "our", "food", "5", "min", "before", "we", "had", "to", "leave", "to", "go", "back", "to", "work", "and", "one", "of", "our", "orders", "got", "lost\\/was", "forgotten", "-LRB-", "most", "of", "us", "only", "get", "a", "60", "min", "break", "for", "lunch", "so", "no", "time", "to", "get", "lunch", "sonewhere", "else", "-RRB-", "."], "e1_text": "got", "e1_pos": 9, "e2_text": "had", "e2_pos": 16, "label": "before"},
{"tokens": ["We", "waited", "for", "50", "min", ",", "other", "tables", "were", "served", "before", "we", "got", "our", "food", "-LRB-", "and", "some", "of", "them", "arrived", "after", "we", "did", "-RRB-", "and", "5", "min", "before", "leaving", ",", "our", "food", "arrived", "."], "e1_text": "served", "e1_pos": 9, "e2_text": "got", "e2_pos": 12, "label": "before"},
{"tokens": ["I", "work", "Downtown", "and", "I", "can", "get", "yummy", "food", "close", "by", "without", "having", "to", "drive\\/wait", "for", "over", "45", "min", "to", "end", "up", "either", "eating", "super", "fast", "before", "I", "have", "to", "go", "and", "not", "enjoying", "my", "food", "-LRB-", "which", "is", "the", "main", "reason", "to", "get", "out", "of", "the", "office", "-RRB-", "or", "taking", "my", "food", "to", "go", "and", "eating", "it", "on", "my", "desk", ",", "which", "is", "what", "I", "want", "to", "avoid", "when", "I", "go", "out", "to", "eat", "."], "e1_text": "eating", "e1_pos": 23, "e2_text": "have", "e2_pos": 28, "label": "before"}
]
