[
{"tokens": ["Do", "n't", "stay", "here", "and", "gamble", "and", "expect", "any", "comps", "they", "lured", "me", "in", "with", "costly", "hotel", "rates", "and", "pretending", "your", "bill", "will", "be", "taken", "care", "of", "and", "after", "losing", "several", "thousand", "dollars", "there", "they", "still", "charged", "me", "full", "rate", "and", "when", "they", "told", "me", "I", "earned", "free", "comps", "they", "suddenly", "all", "disappeared", "."], "e1_text": "taken", "e1_pos": 24, "e2_text": "losing", "e2_pos": 29, "label": "after"}
]
