[
{"tokens": ["And", "it", "was", "every", "dish", "...", "So", "either", "the", "chef", "does", "n't", "try", "what", "he", "'s", "serving", ",", "or", "they", "do", "n't", "actually", "care", "what", "the", "food", "tastes", "like", "because", "after", "all", "this", "is", "a", "bar", ",", "and", "we", "should", "be", "thankful", "that", "they", "serve", "something", "to", "eat", "in", "the", "first", "place", "...", "On", "the", "drinking", "end", ",", "they", "had", "a", "large", "menu", ",", "but", "we", "stuck", "with", "a", "few", "bottles", "of", "wine", "so", "ca", "n't", "really", "comment", "on", "the", "drinks", ".", "."], "e1_text": "like", "e1_pos": 28, "e2_text": "is", "e2_pos": 33, "label": "after"}
]
