[
{"tokens": ["I", "had", "to", "stop", "payment", "through", "my", "CC", "because", "Martins", "Doors", "-LRB-", "Garage", "-RRB-", "which", "I", "needed", "one", "and", "after", "telling", "the", "worker", "Ryan", "that", "I", "need", "to", "match", "the", "color", "of", "the", "other", "doors", "in", "the", "development", "which", "are", "a", "light", "Tan", "which", "most", "house", "'s", "have", "and", "some", "have", "a", "light", "green", "."], "e1_text": "stop", "e1_pos": 3, "e2_text": "telling", "e2_pos": 20, "label": "after"}
]
