[
{"tokens": ["Hotdog", "would", "be", "a", "4", "-LRB-", "once", "they", "got", "the", "order", "right", "-RRB-", ",", "but", "since", "that", "took", "sometime", "for", "that", "we", "will", "give", "it", "a", "2", "Chili", "cheese", "fries", ",", "it", "it", "was", "melted", "cheese", "would", "'ve", "been", "a", "5", ",", "but", "it", "'s", "like", "shredded", "cheese", "that", "was", "n't", "melted", "enough", "--", "3", "Ordering-1", "So", "after", "a", "morning", "of", "watching", "football", "and", "gambling", "on", "a", "Sunday", "we", "wanted", "drunk", "food", "."], "e1_text": "was", "e1_pos": 33, "e2_text": "watching", "e2_pos": 61, "label": "after"}
]
