[
{"tokens": ["I", "told", "her", "someone", "had", "to", "be", "held", "accountable", "for", "not", "placing", "the", "order", "correctly", "in", "the", "first", "place", ",", "meaning", "that", "a", "manager", "should", "'ve", "come", "out", "-LRB-", "I", "saw", "that", "they", "were", "there", "the", "day", "we", "went", "to", "place", "the", "order", "-RRB-", "and", "made", "sure", "it", "was", "correct", "with", "us", "before", "placing", "it", "in", "the", "first", "place", "."], "e1_text": "was", "e1_pos": 48, "e2_text": "placing", "e2_pos": 11, "label": "before"}
]
