[
{"tokens": ["After", "I", "picked", "the", "specific", "brand", "up", "and", "declined", "on", "''", "``", "upgrading", "''", "''", "to", "the", "performance", "blades", "-LRB-", "that", "were", "not", "but", "1", "get", "1", ",", "funny", "enough", "-RRB-", "I", "was", "informed", "that", "the", "buy", "1", "get", "1", "sale", "was", "not", "in", "effect", "until", "tomorrow", "...", "...", "Having", "worked", "in", "retail", "before", ",", "it", "is", "common", "practice", "for", "a", "misrepresented", "sale", "-LRB-", "most", "often", "from", "a", "sale", "display", "being", "left", "up", "too", "long", "--", "this", "case", "being", "displayed", "prematurely", "-RRB-", "to", "be", "overridden", "by", "the", "manager", "."], "e1_text": "retail", "e1_pos": 52, "e2_text": "is", "e2_pos": 56, "label": "before"}
]
